glove_semantic_explorer/__main__.py
glove_semantic_explorer/cli.py
glove_semantic_explorer/templates.py
glove_semantic_explorer-0.1.1.dist-info/LICENSE
glove_semantic_explorer-0.1.1.dist-info/METADATA
glove_semantic_explorer-0.1.1.dist-info/WHEEL
glove_semantic_explorer-0.1.1.dist-info/RECORD
